gamepad/__init__.py
gamepad/cli.py
gamepad/gamepad.py
gamepad-0.1.1.dist-info/DESCRIPTION.rst
gamepad-0.1.1.dist-info/METADATA
gamepad-0.1.1.dist-info/RECORD
gamepad-0.1.1.dist-info/WHEEL
gamepad-0.1.1.dist-info/entry_points.txt
gamepad-0.1.1.dist-info/metadata.json
gamepad-0.1.1.dist-info/top_level.txt
