Metadata-Version: 2.0
Name: gamepad
Version: 0.1.1
Summary: 
Home-page: https://github.com/DariusMontez/gamepad
Author: Darius Montez
Author-email: darius.montez@gmail.com
License: MIT license
Keywords: gamepad
Platform: UNKNOWN
Classifier: Development Status :: 2 - Pre-Alpha
Classifier: Intended Audience :: Developers
Classifier: License :: OSI Approved :: MIT License
Classifier: Natural Language :: English
Classifier: Programming Language :: Python :: 3
Classifier: Programming Language :: Python :: 3.4
Classifier: Programming Language :: Python :: 3.5
Classifier: Programming Language :: Python :: 3.6
Requires-Python: >=3
Requires-Dist: Click (>=6.0)
